pyhentai/__init__.py
pyhentai/pyhentai.py
pyhentai_dwnppo-0.0.1.dist-info/LICENSE
pyhentai_dwnppo-0.0.1.dist-info/METADATA
pyhentai_dwnppo-0.0.1.dist-info/WHEEL
pyhentai_dwnppo-0.0.1.dist-info/top_level.txt
pyhentai_dwnppo-0.0.1.dist-info/RECORD
